markdown_scrolly/__init__.py
markdown_scrolly/animation.py
markdown_scrolly/cli.py
markdown_scrolly/mdparser.py
markdown_scrolly/resources/anima.js
markdown_scrolly/resources/anima_base.css
markdown_scrolly/resources/anima_build.css
markdown_scrolly/resources/md.css
markdown_scrolly-0.3.3.dist-info/LICENSE
markdown_scrolly-0.3.3.dist-info/METADATA
markdown_scrolly-0.3.3.dist-info/WHEEL
markdown_scrolly-0.3.3.dist-info/entry_points.txt
markdown_scrolly-0.3.3.dist-info/top_level.txt
markdown_scrolly-0.3.3.dist-info/RECORD
