Metadata-Version: 2.2
Name: markdown-scrolly
Version: 0.3.3
Summary: MD renderer for control aestetics using CSS and to include simple scroll animations.
Author-email: Willy Pregliasco <willy.pregliasco@gmail.com>
License: MIT License
Project-URL: Gitlab Page, https://gitlab.com/wpregliasco/markdown-scrolly
Project-URL: Bug Tracker, https://gitlab.com/wpregliasco/markdown-scrolly/-/issues
Classifier: Programming Language :: Python :: 3
Classifier: License :: OSI Approved :: MIT License
Classifier: Operating System :: OS Independent
Requires-Python: <4.0,>=3.9
License-File: LICENSE
Requires-Dist: markdown
Requires-Dist: html-packager<0.2.0,>=0.1.6
